{"config":{"output_file":null,"full_docs":false,"pub_only":false,"reachable_only":false,"distro_crate":false,"signatures":false,"borrow_data":false},"version":"0.19.1","compilation":{"directory":"/Users/tyco/Documents/GitHub/EinsteinDB","program":"/Users/tyco/.rustup/toolchains/stable-x86_64-apple-darwin/bin/rls","arguments":[],"output":"/Users/tyco/Documents/GitHub/EinsteinDB/target/rls/debug/deps/libeinsteindb-221dcc1b6b2c01df.rmeta"},"prelude":{"crate_id":{"name":"einsteindb","disambiguator":[14557823626752417892,0]},"crate_root":"src","external_crates":[{"file_name":"/Users/tyco/Documents/GitHub/EinsteinDB/src/main.rs","num":1,"id":{"name":"std","disambiguator":[5737620048972976797,0]}},{"file_name":"/Users/tyco/Documents/GitHub/EinsteinDB/src/main.rs","num":2,"id":{"name":"core","disambiguator":[2242199718071837415,0]}},{"file_name":"/Users/tyco/Documents/GitHub/EinsteinDB/src/main.rs","num":3,"id":{"name":"compiler_builtins","disambiguator":[2188212999151601010,0]}},{"file_name":"/Users/tyco/Documents/GitHub/EinsteinDB/src/main.rs","num":4,"id":{"name":"rustc_std_workspace_core","disambiguator":[1020664553731942337,0]}},{"file_name":"/Users/tyco/Documents/GitHub/EinsteinDB/src/main.rs","num":5,"id":{"name":"alloc","disambiguator":[5221923779696816614,0]}},{"file_name":"/Users/tyco/Documents/GitHub/EinsteinDB/src/main.rs","num":6,"id":{"name":"libc","disambiguator":[10454403582981253701,0]}},{"file_name":"/Users/tyco/Documents/GitHub/EinsteinDB/src/main.rs","num":7,"id":{"name":"unwind","disambiguator":[7392107620293427149,0]}},{"file_name":"/Users/tyco/Documents/GitHub/EinsteinDB/src/main.rs","num":8,"id":{"name":"cfg_if","disambiguator":[9383090470819858406,0]}},{"file_name":"/Users/tyco/Documents/GitHub/EinsteinDB/src/main.rs","num":9,"id":{"name":"hashbrown","disambiguator":[13561338507145107503,0]}},{"file_name":"/Users/tyco/Documents/GitHub/EinsteinDB/src/main.rs","num":10,"id":{"name":"rustc_std_workspace_alloc","disambiguator":[2153887466384468734,0]}},{"file_name":"/Users/tyco/Documents/GitHub/EinsteinDB/src/main.rs","num":11,"id":{"name":"rustc_demangle","disambiguator":[11638676648589799525,0]}},{"file_name":"/Users/tyco/Documents/GitHub/EinsteinDB/src/main.rs","num":12,"id":{"name":"std_detect","disambiguator":[17336646944492823354,0]}},{"file_name":"/Users/tyco/Documents/GitHub/EinsteinDB/src/main.rs","num":13,"id":{"name":"addr2line","disambiguator":[16179365956064936006,0]}},{"file_name":"/Users/tyco/Documents/GitHub/EinsteinDB/src/main.rs","num":14,"id":{"name":"gimli","disambiguator":[2085897901681677768,0]}},{"file_name":"/Users/tyco/Documents/GitHub/EinsteinDB/src/main.rs","num":15,"id":{"name":"object","disambiguator":[4724748409658749452,0]}},{"file_name":"/Users/tyco/Documents/GitHub/EinsteinDB/src/main.rs","num":16,"id":{"name":"memchr","disambiguator":[13513626471981952824,0]}},{"file_name":"/Users/tyco/Documents/GitHub/EinsteinDB/src/main.rs","num":17,"id":{"name":"panic_unwind","disambiguator":[14681960900203760207,0]}},{"file_name":"/Users/tyco/Documents/GitHub/EinsteinDB/src/main.rs","num":18,"id":{"name":"test","disambiguator":[2380924205022762555,0]}},{"file_name":"/Users/tyco/Documents/GitHub/EinsteinDB/src/main.rs","num":19,"id":{"name":"getopts","disambiguator":[910798843940129008,0]}},{"file_name":"/Users/tyco/Documents/GitHub/EinsteinDB/src/main.rs","num":20,"id":{"name":"rustc_std_workspace_std","disambiguator":[15914921874372437732,0]}},{"file_name":"/Users/tyco/Documents/GitHub/EinsteinDB/src/main.rs","num":21,"id":{"name":"unicode_width","disambiguator":[13371626401897226887,0]}}],"span":{"file_name":"src/main.rs","byte_start":0,"byte_end":0,"line_start":0,"line_end":0,"column_start":1,"column_end":1}},"imports":[],"defs":[{"kind":"Mod","id":{"krate":0,"index":0},"span":{"file_name":"src/main.rs","byte_start":0,"byte_end":0,"line_start":0,"line_end":0,"column_start":1,"column_end":1},"name":"","qualname":"::","value":"src/main.rs","parent":null,"children":[{"krate":0,"index":1},{"krate":0,"index":2},{"krate":0,"index":3}],"decl_id":null,"docs":"","sig":null,"attributes":[]}],"impls":[],"refs":[],"macro_refs":[],"relations":[]}